bibtex2html/__init__.py
bibtex2html/__version__.py
bibtex2html/bibtex2html.py
bibtex2html.py-2.3.1.data/scripts/bibtex2html.py
bibtex2html.py-2.3.1.dist-info/DESCRIPTION.rst
bibtex2html.py-2.3.1.dist-info/METADATA
bibtex2html.py-2.3.1.dist-info/RECORD
bibtex2html.py-2.3.1.dist-info/WHEEL
bibtex2html.py-2.3.1.dist-info/metadata.json
bibtex2html.py-2.3.1.dist-info/top_level.txt
