Metadata-Version: 2.0
Name: bibtex2html.py
Version: 2.3.1
Summary: Convert bibtex to html.
Home-page: https://github.com/JianCheng/bibtex2html.py
Author: Jian Cheng
Author-email: jian.cheng.1983@gmail.com
License: BSD
Platform: UNKNOWN
Classifier: License :: OSI Approved :: BSD License
Classifier: Programming Language :: Python
Classifier: Programming Language :: Python :: 2.6
Classifier: Programming Language :: Python :: 2.7
Classifier: Programming Language :: Python :: 3
Classifier: Programming Language :: Python :: 3.3
Classifier: Programming Language :: Python :: 3.4
Classifier: Programming Language :: Python :: 3.5
Classifier: Programming Language :: Python :: 3.6
Classifier: Programming Language :: Python :: Implementation :: CPython
Classifier: Programming Language :: Python :: Implementation :: PyPy
Requires-Dist: bs4
Requires-Dist: bibtexparser
Requires-Dist: docopt
